extra_requirements/requirements-docs.txt
extra_requirements/requirements-tests.txt
reprox/__init__.py
reprox/core.py
reprox/find_runs.py
reprox/process_job.py
reprox/submit_jobs.py
reprox/validate_run.py
reprox-0.2.2.data/scripts/reprox-find-data
reprox-0.2.2.data/scripts/reprox-move-folders
reprox-0.2.2.data/scripts/reprox-reprocess
reprox-0.2.2.data/scripts/reprox-start-jobs
tests/__init__.py
tests/test_bin.py
tests/test_find_runs.py
tests/test_import.py
tests/test_submit_jobs.py
reprox-0.2.2.dist-info/METADATA
reprox-0.2.2.dist-info/WHEEL
reprox-0.2.2.dist-info/top_level.txt
reprox-0.2.2.dist-info/RECORD
