Metadata-Version: 2.1
Name: reprox
Version: 0.2.2
Summary: Reprocessing for XENONnT
Home-page: https://github.com/XENONnT/reprox
Author: J. R. Angevaare
License: UNKNOWN
Platform: UNKNOWN
Classifier: Development Status :: 5 - Production/Stable
Classifier: License :: OSI Approved :: BSD License
Classifier: Natural Language :: English
Classifier: Programming Language :: Python :: 3.8
Classifier: Programming Language :: Python :: 3.9
Classifier: Programming Language :: Python :: 3.10
Classifier: Intended Audience :: Science/Research
Classifier: Programming Language :: Python :: Implementation :: CPython
Classifier: Topic :: Scientific/Engineering :: Physics
Requires-Python: >=3.8
Requires-Dist: strax
Requires-Dist: utilix (>=0.6.6)
Requires-Dist: straxen (>=1.1.0)
Requires-Dist: numba
Requires-Dist: numpy
Requires-Dist: pandas
Provides-Extra: docs
Requires-Dist: autodocsumm (==0.2.7) ; extra == 'docs'
Requires-Dist: commonmark (==0.9.1) ; extra == 'docs'
Requires-Dist: gitpython (==3.1.27) ; extra == 'docs'
Requires-Dist: graphviz (==0.19.1) ; extra == 'docs'
Requires-Dist: m2r (==0.2.1) ; extra == 'docs'
Requires-Dist: nbsphinx (==0.8.8) ; extra == 'docs'
Requires-Dist: numpy (==1.21.0) ; extra == 'docs'
Requires-Dist: recommonmark (==0.7.1) ; extra == 'docs'
Requires-Dist: scipy (==1.7.3) ; extra == 'docs'
Requires-Dist: sphinx-rtd-theme (==1.0.0) ; extra == 'docs'
Requires-Dist: sphinx (==4.4.0) ; extra == 'docs'
Requires-Dist: sphinxcontrib-applehelp (==1.0.2) ; extra == 'docs'
Requires-Dist: sphinxcontrib-devhelp (==1.0.2) ; extra == 'docs'
Requires-Dist: sphinxcontrib-htmlhelp (==2.0.0) ; extra == 'docs'
Requires-Dist: sphinxcontrib-jsmath (==1.0.1) ; extra == 'docs'
Requires-Dist: sphinxcontrib-qthelp (==1.0.3) ; extra == 'docs'
Requires-Dist: typing-extensions (==4.1.1) ; extra == 'docs'
